scrape_up/__init__.py
scrape_up/academia/__init__.py
scrape_up/academia/academia.py
scrape_up/askubuntu/__init__.py
scrape_up/askubuntu/questions.py
scrape_up/banners/__init__.py
scrape_up/banners/scraper88x31.py
scrape_up/bbcnews/__init__.py
scrape_up/bbcnews/bbcnews.py
scrape_up/codechef/__init__.py
scrape_up/codechef/codechef.py
scrape_up/coinmarketcap/__init__.py
scrape_up/coinmarketcap/crypto.py
scrape_up/covidinfo/__init__.py
scrape_up/covidinfo/covidinfo.py
scrape_up/cricbuzz/__init__.py
scrape_up/cricbuzz/cricbuzz.py
scrape_up/devcommunity/__init__.py
scrape_up/devcommunity/articles.py
scrape_up/dribbble/__init__.py
scrape_up/dribbble/dribbble.py
scrape_up/eazydiner/__init__.py
scrape_up/eazydiner/eazydiner.py
scrape_up/ebay/__init__.py
scrape_up/ebay/ebay.py
scrape_up/espn/__init__.py
scrape_up/espn/espnmodule.py
scrape_up/flipkart/__init__.py
scrape_up/flipkart/flipkart_clothing.py
scrape_up/flipkart/flipkart_file.py
scrape_up/flipkart/flipkart_laptop.py
scrape_up/flyrobu/__init__.py
scrape_up/flyrobu/flyrobu.py
scrape_up/github/__init__.py
scrape_up/github/issue.py
scrape_up/github/organization.py
scrape_up/github/pull_request.py
scrape_up/github/repository.py
scrape_up/github/users.py
scrape_up/github_education/__init__.py
scrape_up/github_education/events.py
scrape_up/hackerearth/__init__.py
scrape_up/hackerearth/challenges.py
scrape_up/hackernews/__init__.py
scrape_up/hackernews/articles.py
scrape_up/hackerrank/__init__.py
scrape_up/hackerrank/contest.py
scrape_up/hackerrank/user.py
scrape_up/hashnode/__init__.py
scrape_up/hashnode/hashnode.py
scrape_up/healthgrades/__init__.py
scrape_up/healthgrades/healthgradesmodule.py
scrape_up/icc/__init__.py
scrape_up/icc/icc_rankings.py
scrape_up/imdb/__init__.py
scrape_up/imdb/actor.py
scrape_up/imdb/box_office.py
scrape_up/imdb/celeb.py
scrape_up/imdb/imdb.py
scrape_up/imdb/indian_movies.py
scrape_up/imdb/movie.py
scrape_up-1.1.7.dist-info/LICENSE
scrape_up-1.1.7.dist-info/METADATA
scrape_up-1.1.7.dist-info/WHEEL
scrape_up-1.1.7.dist-info/top_level.txt
scrape_up-1.1.7.dist-info/RECORD
