Metadata-Version: 2.1
Name: scrape-up
Version: 1.1.7
Summary: A web-scraping-based python package that enables you to scrape data from various platforms.
Home-page: https://github.com/Clueless-Community/scrape-up
Author: Clueless Community
Author-email: official.cluelesscommunity@gmail.com
Classifier: Programming Language :: Python :: 3
Classifier: License :: OSI Approved :: MIT License
Classifier: Operating System :: OS Independent
Requires-Python: >=3.6
License-File: LICENSE
Requires-Dist: bs4
Requires-Dist: requests
Requires-Dist: requests-html
Requires-Dist: beautifulsoup4
